adop/__init__.py
adop/__main__.py
adop/api_client.py
adop/auto_fetch.py
adop/auto_fetch_state.py
adop/auto_sequences.py
adop/cache_state.py
adop/deploy_state.py
adop/downloaders.py
adop/exceptions.py
adop/hooks.py
adop/logging.py
adop/parse_config.py
adop/restapi.py
adop/setup_config_command.py
adop/setup_rest_api.py
adop/setup_zip_command.py
adop/store_payload.py
adop/tags.py
adop/unpack_payload.py
adop/uploaders.py
adop/verify_payload.py
adop/zip_deploy_sequences.py
adop/zip_import.py
adop/zip_install.py
adop/zip_install_sequences.py
adop/zip_upload.py
adop/tool/__init__.py
adop/tool/hg.py
adop-0.0.9.dist-info/LICENSE.rst
adop-0.0.9.dist-info/METADATA
adop-0.0.9.dist-info/WHEEL
adop-0.0.9.dist-info/entry_points.txt
adop-0.0.9.dist-info/top_level.txt
adop-0.0.9.dist-info/RECORD
