Metadata-Version: 2.1
Name: adop
Version: 0.0.9
Summary: Automatic deployment on-prem from zip archives
Home-page: https://gitlab.com/fholmer/adop
Author: Frode Holmer
Author-email: fholmer+adop@gmail.com
License: BSD-3-Clause
Project-URL: Documentation, https://fholmer.gitlab.io/adop
Project-URL: Source Code, https://gitlab.com/fholmer/adop
Keywords: rest,api,post,zip,auto,deploy,on-prem
Classifier: Development Status :: 4 - Beta
Classifier: Environment :: Web Environment
Classifier: Intended Audience :: Developers
Classifier: License :: OSI Approved :: BSD License
Classifier: Operating System :: OS Independent
Classifier: Programming Language :: Python :: 3
Classifier: Programming Language :: Python :: 3.9
Classifier: Programming Language :: Python :: 3.10
Classifier: Programming Language :: Python :: 3.11
License-File: LICENSE.rst
Provides-Extra: server
Requires-Dist: Flask (==2.1.*) ; extra == 'server'
Requires-Dist: waitress (==2.1.*) ; extra == 'server'
